raijin_server/__init__.py
raijin_server/cli.py
raijin_server/config.py
raijin_server/healthchecks.py
raijin_server/module_manager.py
raijin_server/utils.py
raijin_server/validators.py
raijin_server/modules/__init__.py
raijin_server/modules/apokolips_demo.py
raijin_server/modules/bootstrap.py
raijin_server/modules/calico.py
raijin_server/modules/cert_manager.py
raijin_server/modules/essentials.py
raijin_server/modules/firewall.py
raijin_server/modules/full_install.py
raijin_server/modules/grafana.py
raijin_server/modules/hardening.py
raijin_server/modules/harness.py
raijin_server/modules/istio.py
raijin_server/modules/kafka.py
raijin_server/modules/kong.py
raijin_server/modules/kubernetes.py
raijin_server/modules/loki.py
raijin_server/modules/metallb.py
raijin_server/modules/minio.py
raijin_server/modules/network.py
raijin_server/modules/observability_dashboards.py
raijin_server/modules/observability_ingress.py
raijin_server/modules/prometheus.py
raijin_server/modules/sanitize.py
raijin_server/modules/secrets.py
raijin_server/modules/ssh_hardening.py
raijin_server/modules/traefik.py
raijin_server/modules/velero.py
raijin_server/modules/vpn.py
raijin_server/scripts/__init__.py
raijin_server/scripts/checklist.sh
raijin_server/scripts/install.sh
raijin_server/scripts/log_size_metric.sh
raijin_server/scripts/pre-deploy-check.sh
raijin_server-0.2.41.dist-info/licenses/LICENSE
raijin_server-0.2.41.dist-info/METADATA
raijin_server-0.2.41.dist-info/WHEEL
raijin_server-0.2.41.dist-info/entry_points.txt
raijin_server-0.2.41.dist-info/top_level.txt
raijin_server-0.2.41.dist-info/RECORD
